plone.app.collection-1.2.7-py2.7-nspkg.pth
plone/app/collection/__init__.py
plone/app/collection/collection.py
plone/app/collection/config.py
plone/app/collection/configure.zcml
plone/app/collection/field.py
plone/app/collection/integration.py
plone/app/collection/interfaces.py
plone/app/collection/marshaller.py
plone/app/collection/testing.py
plone/app/collection/testing_keywords.py
plone/app/collection/validators.py
plone/app/collection/browser/__init__.py
plone/app/collection/browser/configure.zcml
plone/app/collection/browser/templates/all_content.pt
plone/app/collection/browser/templates/rss.pt
plone/app/collection/browser/templates/standard_view.pt
plone/app/collection/browser/templates/summary_view.pt
plone/app/collection/browser/templates/tabular_view.pt
plone/app/collection/browser/templates/thumbnail_view.pt
plone/app/collection/portlets/__init__.py
plone/app/collection/portlets/collectionportlet.py
plone/app/collection/profiles/default/factorytool.xml
plone/app/collection/profiles/default/metadata.xml
plone/app/collection/profiles/default/rolemap.xml
plone/app/collection/profiles/default/types.xml
plone/app/collection/profiles/default/types/Collection.xml
plone/app/collection/profiles/uninstall/types.xml
plone/app/collection/tests/__init__.py
plone/app/collection/tests/image.png
plone/app/collection/tests/test_collection.py
plone/app/collection/tests/test_robot.py.txt
plone/app/collection/tests/acceptance/collection_keywords.txt
plone/app/collection/tests/acceptance/test_collection.txt
plone/app/collection/tests/robot/keywords.txt
plone/app/collection/tests/robot/robot_collection.txt
plone.app.collection-1.2.7.dist-info/METADATA
plone.app.collection-1.2.7.dist-info/RECORD
plone.app.collection-1.2.7.dist-info/WHEEL
plone.app.collection-1.2.7.dist-info/entry_points.txt
plone.app.collection-1.2.7.dist-info/namespace_packages.txt
plone.app.collection-1.2.7.dist-info/top_level.txt
