Metadata-Version: 2.1
Name: plone.app.collection
Version: 1.2.7
Summary: This package adds 'saved search' functionality to Plone.
Home-page: https://pypi.org/project/plone.app.collection
Author: Plone Foundation
Author-email: plone-developers@lists.sourceforge.net
License: GPL version 2
Keywords: plone collection topic smartfolder saved search
Platform: UNKNOWN
Classifier: Framework :: Plone
Classifier: Framework :: Plone :: 5.1
Classifier: Framework :: Plone :: 5.2
Classifier: License :: OSI Approved :: GNU General Public License v2 (GPLv2)
Classifier: Programming Language :: Python
Classifier: Programming Language :: Python :: 2.7
Provides-Extra: test
Requires-Dist: setuptools
Requires-Dist: plone.app.contentlisting
Requires-Dist: plone.app.portlets
Requires-Dist: plone.app.querystring (>=1.2.2)
Requires-Dist: plone.app.vocabularies
Requires-Dist: plone.app.widgets
Requires-Dist: plone.portlet.collection
Requires-Dist: plone.portlets
Requires-Dist: Products.Archetypes (>=1.10.4.dev0)
Requires-Dist: Products.CMFCore
Requires-Dist: Products.CMFPlone
Requires-Dist: Products.validation
Requires-Dist: transaction
Requires-Dist: zope.component
Requires-Dist: zope.configuration
Requires-Dist: zope.i18nmessageid
Requires-Dist: zope.interface
Requires-Dist: zope.schema
Requires-Dist: Zope2
Provides-Extra: test
Requires-Dist: plone.app.testing[robot]; extra == 'test'
Requires-Dist: Products.ATContentTypes[test]; extra == 'test'
